month/__init__.py
month/forms.py
month/models.py
month/tests.py
month/util.py
month/widgets.py
month/locale/pt_BR/LC_MESSAGES/django.mo
month/locale/pt_BR/LC_MESSAGES/django.po
month/static/month/field/widget_month.css
django_monthfield-0.1.2.dist-info/LICENSE
django_monthfield-0.1.2.dist-info/METADATA
django_monthfield-0.1.2.dist-info/WHEEL
django_monthfield-0.1.2.dist-info/top_level.txt
django_monthfield-0.1.2.dist-info/RECORD
