Metadata-Version: 2.1
Name: django-monthfield
Version: 0.1.2
Summary: Provides a field for storing months (YYYY-MM) on django models.
Home-page: https://github.com/clearspark/django-monthfield
Author: Matthys Kroon
Author-email: matthysk@clearspark.co.za
License: BSD licence, see LICENCE
Platform: UNKNOWN
